<?xml version="1.0" encoding="UTF-8"?>
<edges>
    <!-- MAIN CATEGORIES -->
    
    <!-- kTERM_NAMESPACES -->
    <edge>
    	<element variable="kTAG_SUBJECT">:NAMESPACES</element>
    	<element variable="kTAG_PREDICATE">:SUBCLASS-OF</element>
    	<element variable="kTAG_OBJECT">:ONTOLOGY</element>
    </edge>
    
    <!-- kTERM_ENUMERATIONS -->
	<edge>
    	<element variable="kTAG_SUBJECT">:ENUMERATIONS</element>
    	<element variable="kTAG_PREDICATE">:SUBCLASS-OF</element>
    	<element variable="kTAG_OBJECT">:ONTOLOGY</element>
    </edge>
    
    <!-- kTERM_PREDICATES -->
	<edge>
    	<element variable="kTAG_SUBJECT">:PREDICATES</element>
    	<element variable="kTAG_PREDICATE">:SUBCLASS-OF</element>
    	<element variable="kTAG_OBJECT">:ONTOLOGY</element>
    </edge>
    
	<!-- kTERM_ATTRIBUTES -->
	<edge>
    	<element variable="kTAG_SUBJECT">:ATTRIBUTES</element>
    	<element variable="kTAG_PREDICATE">:SUBCLASS-OF</element>
    	<element variable="kTAG_OBJECT">:ONTOLOGY</element>
    </edge>
    
    <!-- ENUMERATION CATEGORY EDGES -->
     
	<!-- kTERM_TYPES -->
	<edge>
    	<element variable="kTAG_SUBJECT">:TYPES</element>
    	<element variable="kTAG_PREDICATE">:SUBCLASS-OF</element>
    	<element variable="kTAG_OBJECT">:ENUMERATIONS</element>
    </edge>
     
	<!-- kTERM_KINDS -->
	<edge>
    	<element variable="kTAG_SUBJECT">:KINDS</element>
    	<element variable="kTAG_PREDICATE">:SUBCLASS-OF</element>
    	<element variable="kTAG_OBJECT">:ENUMERATIONS</element>
    </edge>
     
	<!-- kTERM_STATES -->
	<edge>
    	<element variable="kTAG_SUBJECT">:STATES</element>
    	<element variable="kTAG_PREDICATE">:SUBCLASS-OF</element>
    	<element variable="kTAG_OBJECT">:ENUMERATIONS</element>
    </edge>
     
	<!-- kTERM_OPERATORS -->
	<edge>
    	<element variable="kTAG_SUBJECT">:OPERATORS</element>
    	<element variable="kTAG_PREDICATE">:SUBCLASS-OF</element>
    	<element variable="kTAG_OBJECT">:ENUMERATIONS</element>
    </edge>
   
    <!-- TYPE CATEGORY TERMS -->
     
	<!-- kTERM_PRIMITIVES -->
	<edge>
    	<element variable="kTAG_SUBJECT">:PRIMITIVES</element>
    	<element variable="kTAG_PREDICATE">:SUBCLASS-OF</element>
    	<element variable="kTAG_OBJECT">:TYPES</element>
    </edge>
     
	<!-- kTERM_STRUCTURES -->
	<edge>
    	<element variable="kTAG_SUBJECT">:STRUCTURES</element>
    	<element variable="kTAG_PREDICATE">:SUBCLASS-OF</element>
    	<element variable="kTAG_OBJECT">:TYPES</element>
    </edge>
     
	<!-- kTERM_ENUMERATED -->
	<edge>
    	<element variable="kTAG_SUBJECT">:ENUMERATED</element>
    	<element variable="kTAG_PREDICATE">:SUBCLASS-OF</element>
    	<element variable="kTAG_OBJECT">:TYPES</element>
    </edge>
     
	<!-- kTERM_CARDINALITY -->
	<edge>
    	<element variable="kTAG_SUBJECT">:CARDINALITY</element>
    	<element variable="kTAG_PREDICATE">:SUBCLASS-OF</element>
    	<element variable="kTAG_OBJECT">:TYPES</element>
    </edge>
     
	<!-- kTERM_RELATIONSHIP -->
	<edge>
    	<element variable="kTAG_SUBJECT">:RELATIONSHIP</element>
    	<element variable="kTAG_PREDICATE">:SUBCLASS-OF</element>
    	<element variable="kTAG_OBJECT">:TYPES</element>
    </edge>
    
    <!-- ATTRIBUTE CATEGORY TERMS -->
     
	<!-- kTERM_IDENTIFICATION -->
	<edge>
    	<element variable="kTAG_SUBJECT">:IDENTIFICATION</element>
    	<element variable="kTAG_PREDICATE">:SUBCLASS-OF</element>
    	<element variable="kTAG_OBJECT">:ATTRIBUTES</element>
    </edge>
     
	<!-- kTERM_REFERENCE -->
	<edge>
    	<element variable="kTAG_SUBJECT">:REFERENCE</element>
    	<element variable="kTAG_PREDICATE">:SUBCLASS-OF</element>
    	<element variable="kTAG_OBJECT">:ATTRIBUTES</element>
    </edge>
     
	<!-- kTERM_CLASSIFICATION -->
	<edge>
    	<element variable="kTAG_SUBJECT">:CLASSIFICATION</element>
    	<element variable="kTAG_PREDICATE">:SUBCLASS-OF</element>
    	<element variable="kTAG_OBJECT">:ATTRIBUTES</element>
    </edge>
     
	<!-- kTERM_ILLUSTRATION -->
	<edge>
    	<element variable="kTAG_SUBJECT">:ILLUSTRATION</element>
    	<element variable="kTAG_PREDICATE">:SUBCLASS-OF</element>
    	<element variable="kTAG_OBJECT">:ATTRIBUTES</element>
    </edge>
     
	<!-- kTERM_AUTHORSHIP -->
	<edge>
    	<element variable="kTAG_SUBJECT">:AUTHORSHIP</element>
    	<element variable="kTAG_PREDICATE">:SUBCLASS-OF</element>
    	<element variable="kTAG_OBJECT">:ATTRIBUTES</element>
    </edge>
     
	<!-- kTERM_STATUS -->
	<edge>
    	<element variable="kTAG_SUBJECT">:STATUS</element>
    	<element variable="kTAG_PREDICATE">:SUBCLASS-OF</element>
    	<element variable="kTAG_OBJECT">:ATTRIBUTES</element>
    </edge>
</edges>